<?xml version="1.0" encoding="utf-8"?>
<Assets Count="2">
  <Asset>
    <Template>RepairCrane</Template>
    <Values>
      <Standard>
        <GUID>1010525</GUID>
        <Name>harbor_07 (Repair Crane)</Name>
        <IconFilename>data/ui/2kimages/main/3dicons/icon_repair_crane.png</IconFilename>
        <InfoDescription>3065</InfoDescription>
      </Standard>
      <Building>
        <BuildingCategoryName>11150</BuildingCategoryName>
        <AssociatedRegions>Moderate</AssociatedRegions>
      </Building>
      <Blocking>
        <GroundDecalAsset>100446</GroundDecalAsset>
        <GroundDecalInvisible>101008</GroundDecalInvisible>
        <HasBuildingBaseTiles>1</HasBuildingBaseTiles>
      </Blocking>
      <Mesh />
      <Object>
        <Variations>
          <Item>
            <Filename>data/graphics/buildings/special/harbor_07/harbor_07.cfg</Filename>
          </Item>
        </Variations>
      </Object>
      <AmbientMoodProvider />
      <Constructable />
      <Selection>
        <GUIType>Military</GUIType>
      </Selection>
      <Text>
        <LocaText>
          <English>
            <Text>Repair Crane</Text>
            <Status>Exported</Status>
            <ExportCount>1</ExportCount>
          </English>
        </LocaText>
        <LineID>7021</LineID>
      </Text>
      <Cost>
        <Costs>
          <Item>
            <Ingredient>1010017</Ingredient>
            <Amount>2500</Amount>
          </Item>
          <Item>
            <Ingredient>1010196</Ingredient>
            <Amount>15</Amount>
          </Item>
          <Item>
            <Ingredient>1010205</Ingredient>
            <Amount>15</Amount>
          </Item>
          <Item>
            <Ingredient>1010218</Ingredient>
            <Amount>25</Amount>
          </Item>
          <Item>
            <Ingredient>1010207</Ingredient>
          </Item>
          <Item>
            <Ingredient>1010202</Ingredient>
          </Item>
        </Costs>
        <InfluenceCostType>DefenseBuilding</InfluenceCostType>
      </Cost>
      <Attackable>
        <MaximumHitPoints>4000</MaximumHitPoints>
        <HPBarOffset>6.5</HPBarOffset>
        <HasRuinState>1</HasRuinState>
        <PausedTimeIfAttacked>0</PausedTimeIfAttacked>
        <SelfHealPerHealTick>5</SelfHealPerHealTick>
        <DefenseByAIFactor>201</DefenseByAIFactor>
        <TakeOverEffect>OnDeath</TakeOverEffect>
        <MoralePower>50</MoralePower>
        <IslandWarFlag>102308</IslandWarFlag>
        <ExplosionEffects>
          <Item>
            <VectorElement>
              <InheritedIndex>0</InheritedIndex>
              <InheritanceMapV2>
                <Entry>
                  <TemplateName>RepairCrane</TemplateName>
                  <Index>0</Index>
                </Entry>
              </InheritanceMapV2>
            </VectorElement>
            <ExplosionEffectFilePath>data/graphics/effects/military/explosions/harbor_generic_xpl_02.cfg</ExplosionEffectFilePath>
          </Item>
        </ExplosionEffects>
        <ExplosionEffectsMin>1</ExplosionEffectsMin>
        <ExplosionEffectsMax>1</ExplosionEffectsMax>
        <MilitaryDefensePoints>1.5</MilitaryDefensePoints>
      </Attackable>
      <Infolayer />
      <Maintenance>
        <Maintenances>
          <Item>
            <Product>1010017</Product>
            <Amount>50</Amount>
            <InactiveAmount>25</InactiveAmount>
          </Item>
        </Maintenances>
      </Maintenance>
      <Locked />
      <RepairCrane>
        <HealRadius>20</HealRadius>
        <HealPerMinute>600</HealPerMinute>
        <HealBuildingsPerMinute>600</HealBuildingsPerMinute>
      </RepairCrane>
      <Pausable />
      <DelayedConstruction />
      <SoundEmitter>
        <ActiveSounds>
          <Item>
            <Sound>200896</Sound>
          </Item>
        </ActiveSounds>
        <ConstructionSounds>
          <BuildSuccessful>
            <Item>
              <Sound>206544</Sound>
            </Item>
          </BuildSuccessful>
        </ConstructionSounds>
        <BuildingRuined>
          <Item>
            <Sound>203848</Sound>
          </Item>
        </BuildingRuined>
        <BuildingRepaired>
          <Item>
            <Sound>203866</Sound>
          </Item>
        </BuildingRepaired>
      </SoundEmitter>
      <UpgradeList />
      <FeedbackController />
    </Values>
  </Asset>
  <Asset>
    <BaseAssetGUID>1010525</BaseAssetGUID>
    <Values>
      <Standard>
        <GUID>101573</GUID>
        <Name>harbor_colony01_07 (Repair Crane)</Name>
      </Standard>
      <Building>
        <AssociatedRegions>Colony01</AssociatedRegions>
      </Building>
      <Blocking>
        <GroundDecalAsset>102460</GroundDecalAsset>
        <GroundDecalInvisible>102459</GroundDecalInvisible>
      </Blocking>
      <Mesh />
      <Object>
        <Variations>
          <Item>
            <Filename>data/graphics/buildings/special/harbor_07_colony_01/harbor_07_colony_01.cfg</Filename>
          </Item>
        </Variations>
      </Object>
      <AmbientMoodProvider />
      <Constructable />
      <Selection />
      <Text>
        <LineID>14138</LineID>
      </Text>
      <Cost>
        <Costs>
          <Item>
            <VectorElement>
              <InheritedIndex>0</InheritedIndex>
              <InheritanceMapV2>
                <Entry>
                  <TemplateName>RepairCrane</TemplateName>
                  <Index>0</Index>
                </Entry>
              </InheritanceMapV2>
            </VectorElement>
            <Amount>500</Amount>
          </Item>
          <Item>
            <VectorElement>
              <InheritedIndex>1</InheritedIndex>
              <InheritanceMapV2>
                <Entry>
                  <TemplateName>RepairCrane</TemplateName>
                  <Index>1</Index>
                </Entry>
              </InheritanceMapV2>
            </VectorElement>
            <Amount>50</Amount>
          </Item>
          <Item>
            <VectorElement>
              <InheritedIndex>2</InheritedIndex>
              <InheritanceMapV2>
                <Entry>
                  <TemplateName>RepairCrane</TemplateName>
                  <Index>2</Index>
                </Entry>
              </InheritanceMapV2>
            </VectorElement>
            <Amount>75</Amount>
          </Item>
          <Item>
            <VectorElement>
              <InheritedIndex>3</InheritedIndex>
              <InheritanceMapV2>
                <Entry>
                  <TemplateName>RepairCrane</TemplateName>
                  <Index>3</Index>
                </Entry>
              </InheritanceMapV2>
            </VectorElement>
            <Amount>0</Amount>
          </Item>
          <Item>
            <VectorElement>
              <InheritedIndex>4</InheritedIndex>
              <InheritanceMapV2>
                <Entry>
                  <TemplateName>RepairCrane</TemplateName>
                  <Index>4</Index>
                </Entry>
              </InheritanceMapV2>
            </VectorElement>
          </Item>
          <Item>
            <VectorElement>
              <InheritedIndex>5</InheritedIndex>
              <InheritanceMapV2>
                <Entry>
                  <TemplateName>RepairCrane</TemplateName>
                  <Index>5</Index>
                </Entry>
              </InheritanceMapV2>
            </VectorElement>
          </Item>
        </Costs>
      </Cost>
      <Attackable />
      <Infolayer />
      <Maintenance />
      <Locked />
      <RepairCrane />
      <Pausable />
      <DelayedConstruction />
      <SoundEmitter />
      <UpgradeList />
      <FeedbackController />
    </Values>
  </Asset>
</Assets>