<?xml version="1.0" encoding="utf-8"?>
<Assets Count="1">
  <Asset>
    <Template>WinLoseFeature</Template>
    <Values>
      <Standard>
        <GUID>140810</GUID>
        <Name>WinLoseFeature</Name>
        <ID>WinLoseFeature</ID>
        <Comments />
        <InfoDescription>0</InfoDescription>
      </Standard>
      <WinLoseFeature>
        <Bankruptcy>
          <MaxBailoutsBeforeLost>1</MaxBailoutsBeforeLost>
          <BailoutMoney>25000</BailoutMoney>
          <BankruptcyThreshold>-5000</BankruptcyThreshold>
          <BancruptcyNotification>501548</BancruptcyNotification>
        </Bankruptcy>
        <Regicide>
          <KontorAssetPool>100653</KontorAssetPool>
        </Regicide>
        <Monuments>
          <MonumentsAssetPool>130133</MonumentsAssetPool>
        </Monuments>
        <Investors>
          <InvestorPopulationLevel>15000004</InvestorPopulationLevel>
        </Investors>
        <CampaignCondition>
          <ImperialKontorPool>142605</ImperialKontorPool>
        </CampaignCondition>
        <Annhilation>
          <KontorAssetPool>100653</KontorAssetPool>
        </Annhilation>
        <ParticipantLostByAnnihilationNotification>501307</ParticipantLostByAnnihilationNotification>
        <ParticipantLostByBankruptcyNotification>501308</ParticipantLostByBankruptcyNotification>
      </WinLoseFeature>
    </Values>
  </Asset>
</Assets>