[
  {
    "template": "FeedbackVehicle",
    "guid": 1010164,
    "name": "Horse Drawn Carriage 01 (Rear)",
    "id": "",
    "icon": "",
    "description": 0,
    "cost": null,
    "attackable": null,
    "attacker": null,
    "expeditionAttribute": null,
    "shipMaintenance": 0
  },
  {
    "template": "FeedbackVehicle",
    "guid": 1010163,
    "name": "Horse Drawn Carriage 01 (Front)",
    "id": "",
    "icon": "",
    "description": 0,
    "cost": null,
    "attackable": null,
    "attacker": null,
    "expeditionAttribute": null,
    "shipMaintenance": 0
  },
  {
    "template": "FeedbackVehicle",
    "guid": 1010185,
    "name": "Horse Drawn Carriage 06",
    "id": "",
    "icon": "",
    "description": 0,
    "cost": null,
    "attackable": null,
    "attacker": null,
    "expeditionAttribute": null,
    "shipMaintenance": 0
  },
  {
    "template": "FeedbackVehicle",
    "guid": 101959,
    "name": "Steam Carriage",
    "id": "",
    "icon": "",
    "description": 0,
    "cost": null,
    "attackable": null,
    "attacker": null,
    "expeditionAttribute": null,
    "shipMaintenance": 0
  },
  {
    "template": "FeedbackVehicle",
    "guid": 100432,
    "name": "Tourism Ship 01",
    "id": "",
    "icon": "",
    "description": 0,
    "cost": null,
    "attackable": null,
    "attacker": null,
    "expeditionAttribute": null,
    "shipMaintenance": 0
  },
  {
    "template": "FeedbackVehicle",
    "guid": 100433,
    "name": "Tourism Ship 02",
    "id": "",
    "icon": "",
    "description": 0,
    "cost": null,
    "attackable": null,
    "attacker": null,
    "expeditionAttribute": null,
    "shipMaintenance": 0
  },
  {
    "template": "FeedbackVehicle",
    "guid": 100434,
    "name": "Tourism Ship 03",
    "id": "",
    "icon": "",
    "description": 0,
    "cost": null,
    "attackable": null,
    "attacker": null,
    "expeditionAttribute": null,
    "shipMaintenance": 0
  },
  {
    "template": "FeedbackVehicle",
    "guid": 1010158,
    "name": "Tourism Ship",
    "id": "",
    "icon": "data/ui/2kimages/main/3dicons/icon_ship.png",
    "description": 0,
    "cost": null,
    "attackable": null,
    "attacker": null,
    "expeditionAttribute": null,
    "shipMaintenance": 0
  },
  {
    "template": "FeedbackVehicle",
    "guid": 100737,
    "name": "Courier Ship",
    "id": "",
    "icon": "",
    "description": 0,
    "cost": null,
    "attackable": null,
    "attacker": null,
    "expeditionAttribute": null,
    "shipMaintenance": 0
  },
  {
    "template": "FeedbackVehicle",
    "guid": 101660,
    "name": "Fishing Boat",
    "id": "",
    "icon": "data/ui/2kimages/main/3dicons/icon_ship.png",
    "description": 0,
    "cost": null,
    "attackable": null,
    "attacker": null,
    "expeditionAttribute": null,
    "shipMaintenance": 0
  },
  {
    "template": "FeedbackVehicle",
    "guid": 101743,
    "name": "Workforce Ship",
    "id": "",
    "icon": "",
    "description": 0,
    "cost": null,
    "attackable": null,
    "attacker": null,
    "expeditionAttribute": null,
    "shipMaintenance": 0
  },
  {
    "template": "FeedbackVehicle",
    "guid": 102266,
    "name": "Fishing net",
    "id": "",
    "icon": "data/ui/2kimages/main/3dicons/icon_ship.png",
    "description": 0,
    "cost": null,
    "attackable": null,
    "attacker": null,
    "expeditionAttribute": null,
    "shipMaintenance": 0
  },
  {
    "template": "FeedbackVehicle",
    "guid": 1010174,
    "name": "Railway 01",
    "id": "",
    "icon": "",
    "description": 0,
    "cost": null,
    "attackable": null,
    "attacker": null,
    "expeditionAttribute": null,
    "shipMaintenance": 0
  },
  {
    "template": "FeedbackVehicle",
    "guid": 1010175,
    "name": "Railway Cargo 01",
    "id": "",
    "icon": "",
    "description": 0,
    "cost": null,
    "attackable": null,
    "attacker": null,
    "expeditionAttribute": null,
    "shipMaintenance": 0
  },
  {
    "template": "FeedbackVehicle",
    "guid": 1010189,
    "name": "Railway 01 (for camera sequence)",
    "id": "",
    "icon": "",
    "description": 0,
    "cost": null,
    "attackable": null,
    "attacker": null,
    "expeditionAttribute": null,
    "shipMaintenance": 0
  },
  {
    "template": "FeedbackVehicle",
    "guid": 100625,
    "name": "QO Visitor Ship (Tourism)",
    "id": "",
    "icon": "data/ui/2kimages/main/3dicons/icon_ship.png",
    "description": 0,
    "cost": null,
    "attackable": null,
    "attacker": null,
    "expeditionAttribute": null,
    "shipMaintenance": 0
  },
  {
    "template": "FeedbackVehicle",
    "guid": 102386,
    "name": "QO Visitor Ship (Tourism) Escort",
    "id": "",
    "icon": "data/ui/2kimages/main/3dicons/icon_ship.png",
    "description": 0,
    "cost": null,
    "attackable": null,
    "attacker": null,
    "expeditionAttribute": null,
    "shipMaintenance": 0
  },
  {
    "template": "FeedbackVehicle",
    "guid": 101203,
    "name": "CQO_Rowboat_Castaways (Quest Object)",
    "id": "",
    "icon": "data/ui/2kimages/main/3dicons/icon_rowing_boat.png",
    "description": 1083,
    "cost": null,
    "attackable": null,
    "attacker": null,
    "expeditionAttribute": null,
    "shipMaintenance": 0
  }
]