[
  {
    "guid": 1000129,
    "name": "advisor_01 (Hannah Goode)",
    "id": "",
    "icon": "data/ui/2kimages/main/profiles/advisor_01.png",
    "description": 0,
    "portrait": {
      "name": 7,
      "color": "238cc3",
      "isFemale": true
    }
  },
  {
    "guid": 102480,
    "name": "advisor_01 (Hannah Goode Black Dress)",
    "id": "",
    "icon": "data/ui/2kimages/main/profiles/advisor_01.png",
    "description": 0,
    "portrait": {
      "name": 7,
      "color": "238cc3",
      "isFemale": true
    }
  },
  {
    "guid": 1000130,
    "name": "advisor_02 (Aarhant)",
    "id": "",
    "icon": "data/ui/2kimages/main/profiles/advisor_02.png",
    "description": 0,
    "portrait": {
      "name": 31,
      "color": "55915f",
      "isFemale": false
    }
  },
  {
    "guid": 1000131,
    "name": "Colony guy",
    "id": "",
    "icon": "",
    "description": 0,
    "portrait": {
      "name": 0,
      "color": "c42121",
      "isFemale": false
    }
  },
  {
    "guid": 100505,
    "name": "Farmer",
    "id": "FarmerPortrait",
    "icon": "data/ui/2kimages/main/profiles/resident_tier01.png",
    "description": 0,
    "portrait": {
      "name": 0,
      "color": "c42121",
      "isFemale": true
    }
  },
  {
    "guid": 1000166,
    "name": "Worker",
    "id": "",
    "icon": "data/ui/2kimages/main/profiles/portrait_icons_0014_resident_tier02.png",
    "description": 0,
    "portrait": {
      "name": 0,
      "color": "c42121",
      "isFemale": false
    }
  },
  {
    "guid": 100507,
    "name": "Artisan",
    "id": "",
    "icon": "data/ui/2kimages/main/profiles/resident_tier03.png",
    "description": 0,
    "portrait": {
      "name": 0,
      "color": "c42121",
      "isFemale": false
    }
  },
  {
    "guid": 100508,
    "name": "Engineer",
    "id": "",
    "icon": "data/ui/2kimages/main/profiles/resident_tier04.png",
    "description": 0,
    "portrait": {
      "name": 0,
      "color": "c42121",
      "isFemale": true
    }
  },
  {
    "guid": 100509,
    "name": "Investor",
    "id": "Investor",
    "icon": "data/ui/2kimages/main/profiles/resident_tier05.png",
    "description": 0,
    "portrait": {
      "name": 0,
      "color": "c42121",
      "isFemale": false
    }
  },
  {
    "guid": 100460,
    "name": "Captain",
    "id": "CaptainPortrait",
    "icon": "data/ui/2kimages/main/profiles/captain.png",
    "description": 0,
    "portrait": {
      "name": 39,
      "color": "466996",
      "isFemale": false
    }
  },
  {
    "guid": 100675,
    "name": "Visitor",
    "id": "",
    "icon": "data/ui/2kimages/main/profiles/vistor.png",
    "description": 0,
    "portrait": {
      "name": 0,
      "color": "c42121",
      "isFemale": true
    }
  },
  {
    "guid": 100676,
    "name": "Editor",
    "id": "",
    "icon": "data/ui/2kimages/main/profiles/editor.png",
    "description": 0,
    "portrait": {
      "name": 91,
      "color": "c8b482",
      "isFemale": false
    }
  },
  {
    "guid": 100530,
    "name": "ai_01 (Bente Jorgensen)",
    "id": "",
    "icon": "data/ui/2kimages/main/profiles/ai_01.png",
    "description": 0,
    "portrait": {
      "name": 0,
      "color": "c42121",
      "isFemale": true
    }
  },
  {
    "guid": 100663,
    "name": "ai_02 (Princess Qing)",
    "id": "",
    "icon": "data/ui/2kimages/main/profiles/ai_02.png",
    "description": 0,
    "portrait": {
      "name": 0,
      "color": "c42121",
      "isFemale": true
    }
  },
  {
    "guid": 100664,
    "name": "ai_03 (Willie Wibblesock)",
    "id": "",
    "icon": "data/ui/2kimages/main/profiles/ai_03.png",
    "description": 0,
    "portrait": {
      "name": 0,
      "color": "c42121",
      "isFemale": false
    }
  },
  {
    "guid": 100665,
    "name": "ai_04 (George Smith)",
    "id": "",
    "icon": "data/ui/2kimages/main/profiles/ai_04.png",
    "description": 0,
    "portrait": {
      "name": 0,
      "color": "c42121",
      "isFemale": false
    }
  },
  {
    "guid": 100666,
    "name": "ai_05 (Beryl O'Mara)",
    "id": "",
    "icon": "data/ui/2kimages/main/profiles/ai_05.png",
    "description": 0,
    "portrait": {
      "name": 0,
      "color": "c42121",
      "isFemale": true
    }
  },
  {
    "guid": 100667,
    "name": "ai_06 (Artur Gasparov)",
    "id": "",
    "icon": "data/ui/2kimages/main/profiles/ai_06.png",
    "description": 0,
    "portrait": {
      "name": 0,
      "color": "c42121",
      "isFemale": false
    }
  },
  {
    "guid": 100532,
    "name": "ai_07 (Carl Leonard von Malching)",
    "id": "",
    "icon": "data/ui/2kimages/main/profiles/ai_07.png",
    "description": 0,
    "portrait": {
      "name": 0,
      "color": "c42121",
      "isFemale": false
    }
  },
  {
    "guid": 100531,
    "name": "ai_08 (Alonso Graves)",
    "id": "",
    "icon": "data/ui/2kimages/main/profiles/ai_08.png",
    "description": 0,
    "portrait": {
      "name": 0,
      "color": "c42121",
      "isFemale": false
    }
  },
  {
    "guid": 100674,
    "name": "ai_09 (General Vicente Silva)",
    "id": "",
    "icon": "data/ui/2kimages/main/profiles/ai_09.png",
    "description": 0,
    "portrait": {
      "name": 0,
      "color": "c42121",
      "isFemale": false
    }
  },
  {
    "guid": 100588,
    "name": "enemy_01 (Uncle Edvard Goode)",
    "id": "",
    "icon": "data/ui/2kimages/main/profiles/enemy_01.png",
    "description": 0,
    "portrait": {
      "name": 51,
      "color": "aa6432",
      "isFemale": false
    }
  },
  {
    "guid": 100587,
    "name": "enemy_02 (Lady Margaret Hunt)",
    "id": "",
    "icon": "data/ui/2kimages/main/profiles/enemy_02.png",
    "description": 0,
    "portrait": {
      "name": 0,
      "color": "c42121",
      "isFemale": true
    }
  },
  {
    "guid": 100668,
    "name": "3rd_party_01 (Queen)",
    "id": "",
    "icon": "data/ui/2kimages/main/profiles/3rd_party_01.png",
    "description": 0,
    "portrait": {
      "name": 75,
      "color": "e1b423",
      "isFemale": true
    }
  },
  {
    "guid": 100589,
    "name": "3rd_party_02 (Blake)",
    "id": "",
    "icon": "data/ui/2kimages/main/profiles/3rd_party_02.png",
    "description": 0,
    "portrait": {
      "name": 45,
      "color": "b47d50",
      "isFemale": false
    }
  },
  {
    "guid": 100669,
    "name": "3rd_party_03 (Anne Harlow)",
    "id": "",
    "icon": "data/ui/2kimages/main/profiles/3rd_party_03.png",
    "description": 0,
    "portrait": {
      "name": 73,
      "color": "416491",
      "isFemale": true
    }
  },
  {
    "guid": 100670,
    "name": "3rd_party_04 (Toussaint La Fortune)",
    "id": "",
    "icon": "data/ui/2kimages/main/profiles/3rd_party_04.png",
    "description": 0,
    "portrait": {
      "name": 76,
      "color": "3c9687",
      "isFemale": false
    }
  },
  {
    "guid": 100671,
    "name": "3rd_party_05 (Sarmento)",
    "id": "",
    "icon": "data/ui/2kimages/main/profiles/3rd_party_05.png",
    "description": 0,
    "portrait": {
      "name": 29,
      "color": "297d3e",
      "isFemale": true
    }
  },
  {
    "guid": 100672,
    "name": "3rd_party_06 (Old Nate)",
    "id": "",
    "icon": "data/ui/2kimages/main/profiles/3rd_party_06.png",
    "description": 0,
    "portrait": {
      "name": 77,
      "color": "96419b",
      "isFemale": false
    }
  },
  {
    "guid": 100631,
    "name": "3rd_party_07 (Eli Bleakworth)",
    "id": "",
    "icon": "data/ui/2kimages/main/profiles/3rd_party_07.png",
    "description": 0,
    "portrait": {
      "name": 46,
      "color": "c8460f",
      "isFemale": false
    }
  },
  {
    "guid": 100673,
    "name": "3rd_party_08 (Madame Kahina)",
    "id": "",
    "icon": "data/ui/2kimages/main/profiles/3rd_party_08.png",
    "description": 0,
    "portrait": {
      "name": 78,
      "color": "b98250",
      "isFemale": true
    }
  },
  {
    "guid": 101138,
    "name": "campaign_character_01_demolition_expert",
    "id": "",
    "icon": "data/ui/2kimages/main/profiles/campaign_portrait_01.png",
    "description": 0,
    "portrait": {
      "name": 0,
      "color": "c42121",
      "isFemale": false
    }
  },
  {
    "guid": 101300,
    "name": "campaign_character_02_pyrophorian_red",
    "id": "",
    "icon": "data/ui/2kimages/main/profiles/campaign_portrait_pyrophorian.png",
    "description": 0,
    "portrait": {
      "name": 0,
      "color": "c42121",
      "isFemale": false
    }
  },
  {
    "guid": 101301,
    "name": "campaign_character_03_pyrophorian_silver",
    "id": "",
    "icon": "data/ui/2kimages/main/profiles/campaign_portrait_pyrophorianleader.png",
    "description": 0,
    "portrait": {
      "name": 0,
      "color": "c42121",
      "isFemale": false
    }
  },
  {
    "guid": 101302,
    "name": "campaign_character_04_pyrophorian_gold",
    "id": "",
    "icon": "data/ui/2kimages/main/profiles/campaign_portrait_pyrophoriangrandmaster.png",
    "description": 0,
    "portrait": {
      "name": 0,
      "color": "c42121",
      "isFemale": true
    }
  },
  {
    "guid": 101305,
    "name": "campaign_character_05_hannah_sick",
    "id": "",
    "icon": "data/ui/2kimages/main/profiles/advisor_01.png",
    "description": 0,
    "portrait": {
      "name": 0,
      "color": "c42121",
      "isFemale": true
    }
  },
  {
    "guid": 101212,
    "name": "campaign_character_07_magistrate",
    "id": "",
    "icon": "data/ui/2kimages/main/profiles/campaign_portrait_07.png",
    "description": 0,
    "portrait": {
      "name": 0,
      "color": "c42121",
      "isFemale": false
    }
  },
  {
    "guid": 101306,
    "name": "campaign_character_08_cousin_female",
    "id": "",
    "icon": "data/ui/2kimages/main/profiles/resident_tier01.png",
    "description": 0,
    "portrait": {
      "name": 0,
      "color": "c42121",
      "isFemale": true
    }
  },
  {
    "guid": 101307,
    "name": "campaign_character_09_cousin_male",
    "id": "",
    "icon": "data/ui/2kimages/main/profiles/campaign_portrait_09.png",
    "description": 0,
    "portrait": {
      "name": 178,
      "color": "c42121",
      "isFemale": false
    }
  },
  {
    "guid": 101819,
    "name": "Jornalero",
    "id": "",
    "icon": "data/ui/2kimages/main/profiles/resident_colony_tier01.png",
    "description": 0,
    "portrait": {
      "name": 0,
      "color": "c42121",
      "isFemale": false
    }
  },
  {
    "guid": 101820,
    "name": "Obrera",
    "id": "",
    "icon": "data/ui/2kimages/main/profiles/resident_colony_tier02.png",
    "description": 0,
    "portrait": {
      "name": 0,
      "color": "c42121",
      "isFemale": true
    }
  },
  {
    "guid": 101822,
    "name": "Jornalero_atWork",
    "id": "",
    "icon": "data/ui/2kimages/main/profiles/resident_colony_tier01_work.png",
    "description": 0,
    "portrait": {
      "name": 0,
      "color": "c42121",
      "isFemale": false
    }
  },
  {
    "guid": 101823,
    "name": "Obrera_atWork",
    "id": "",
    "icon": "data/ui/2kimages/main/profiles/resident_colony_tier02_work.png",
    "description": 0,
    "portrait": {
      "name": 0,
      "color": "c42121",
      "isFemale": true
    }
  },
  {
    "guid": 101825,
    "name": "Farmer_atWork",
    "id": "",
    "icon": "data/ui/2kimages/main/profiles/resident_tier01.png",
    "description": 0,
    "portrait": {
      "name": 0,
      "color": "c42121",
      "isFemale": true
    }
  },
  {
    "guid": 101826,
    "name": "Worker_atWork",
    "id": "",
    "icon": "data/ui/2kimages/main/profiles/portrait_icons_0014_resident_tier02.png",
    "description": 0,
    "portrait": {
      "name": 0,
      "color": "c42121",
      "isFemale": false
    }
  },
  {
    "guid": 101827,
    "name": "Artisan_atWork",
    "id": "",
    "icon": "data/ui/2kimages/main/profiles/resident_tier03.png",
    "description": 0,
    "portrait": {
      "name": 0,
      "color": "c42121",
      "isFemale": false
    }
  },
  {
    "guid": 101828,
    "name": "Engineer_atWork",
    "id": "",
    "icon": "data/ui/2kimages/main/profiles/resident_tier04.png",
    "description": 0,
    "portrait": {
      "name": 0,
      "color": "c42121",
      "isFemale": true
    }
  },
  {
    "guid": 101829,
    "name": "Investor_atWork",
    "id": "",
    "icon": "data/ui/2kimages/main/profiles/resident_tier05.png",
    "description": 0,
    "portrait": {
      "name": 0,
      "color": "c42121",
      "isFemale": false
    }
  },
  {
    "guid": 101894,
    "name": "General_Enemy",
    "id": "",
    "icon": "data/ui/2kimages/main/profiles/campaign_portrait_11.png",
    "description": 0,
    "portrait": {
      "name": 0,
      "color": "c42121",
      "isFemale": false
    }
  },
  {
    "guid": 102253,
    "name": "Workforce_Commuter_Captain",
    "id": "",
    "icon": "data/ui/2kimages/main/profiles/workforce_captain.png",
    "description": 0,
    "portrait": {
      "name": 0,
      "color": "c42121",
      "isFemale": false
    }
  }
]