<?xml version="1.0" encoding="utf-8"?>
<Assets Count="1">
  <Asset>
    <Template>FireIncident</Template>
    <Values>
      <IncidentFire>
        <BombardmentFireChance>
          <Item>
            <MinHitPointPercentage>50</MinHitPointPercentage>
            <MaxHitPointPercentage>90</MaxHitPointPercentage>
            <FireChance>10</FireChance>
          </Item>
          <Item>
            <MinHitPointPercentage>30</MinHitPointPercentage>
            <MaxHitPointPercentage>50</MaxHitPointPercentage>
            <FireChance>25</FireChance>
          </Item>
          <Item>
            <MinHitPointPercentage>20</MinHitPointPercentage>
            <MaxHitPointPercentage>30</MaxHitPointPercentage>
            <FireChance>50</FireChance>
          </Item>
          <Item>
            <MaxHitPointPercentage>20</MaxHitPointPercentage>
            <FireChance>75</FireChance>
          </Item>
        </BombardmentFireChance>
        <DamagePerFireTick>20</DamagePerFireTick>
        <FireTickRateMs>3000</FireTickRateMs>
      </IncidentFire>
      <Standard>
        <GUID>2001025</GUID>
        <Name>FireIncident</Name>
        <IconFilename>data/ui/2kimages/main/icons/icon_incident_fire.png</IconFilename>
      </Standard>
      <Incident>
        <IncidentMurmur>IncidentFire</IncidentMurmur>
        <IncidentInfolayerIcon>500307</IncidentInfolayerIcon>
        <ResolveInfolayerIcon>500308</ResolveInfolayerIcon>
        <InfectionData>
          <InfectionBaseIntervalMax>40000</InfectionBaseIntervalMax>
          <InfectionLimit>
            <EndGame>
              <Limit>250</Limit>
            </EndGame>
            <LateGame>
              <Limit>150</Limit>
            </LateGame>
            <MidGame>
              <Limit>40</Limit>
            </MidGame>
            <EarlyMidGame>
              <Limit>20</Limit>
            </EarlyMidGame>
            <LateMidGame>
              <Limit>80</Limit>
            </LateMidGame>
          </InfectionLimit>
        </InfectionData>
        <IncidentAttractiveness>
          <BasePerBuilding>0</BasePerBuilding>
          <EscalatedPerBuilding>-50</EscalatedPerBuilding>
        </IncidentAttractiveness>
        <ShipIncidentDefaultDebuff>192004</ShipIncidentDefaultDebuff>
        <ShipIncidentSpreadChance>0</ShipIncidentSpreadChance>
        <InfectionChanceSourceNameMapping>
          <Base>
            <Name>14431</Name>
            <Icon>14431</Icon>
            <NotificationText>14551</NotificationText>
          </Base>
          <Damage>
            <Name>14432</Name>
            <Icon>14432</Icon>
            <NotificationText>14553</NotificationText>
          </Damage>
          <Density>
            <Name>14433</Name>
            <Icon>14433</Icon>
            <NotificationText>14555</NotificationText>
          </Density>
          <HappinessResidence>
            <Name>14434</Name>
            <Icon>14434</Icon>
            <NotificationText>14556</NotificationText>
          </HappinessResidence>
          <Satisfaction>
            <Name>14435</Name>
            <Icon>14435</Icon>
            <NotificationText>14557</NotificationText>
          </Satisfaction>
          <WorkingConditionFactory>
            <Name>14436</Name>
            <Icon>14436</Icon>
            <NotificationText>14558</NotificationText>
          </WorkingConditionFactory>
          <Productivity>
            <Name>14437</Name>
            <Icon>14437</Icon>
            <NotificationText>14559</NotificationText>
          </Productivity>
          <Proximity>
            <Name>14438</Name>
            <Icon>14438</Icon>
            <NotificationText>14560</NotificationText>
          </Proximity>
          <HappinessFactory>
            <Name>14439</Name>
            <Icon>14439</Icon>
            <NotificationText>14561</NotificationText>
          </HappinessFactory>
          <Newspaper>
            <Name>14496</Name>
            <Icon>14496</Icon>
            <NotificationText>14562</NotificationText>
          </Newspaper>
          <Upgrades>
            <Name>14495</Name>
            <Icon>14495</Icon>
            <NotificationText>14563</NotificationText>
          </Upgrades>
          <InfluencerPositive>
            <Name>14497</Name>
            <Icon>14497</Icon>
            <NotificationText>14564</NotificationText>
          </InfluencerPositive>
          <InfluencerNegative>
            <Name>14498</Name>
            <Icon>14498</Icon>
            <NotificationText>14551</NotificationText>
          </InfluencerNegative>
          <WorkingConditionResidence>
            <Name>14436</Name>
            <Icon>14436</Icon>
            <NotificationText>14558</NotificationText>
          </WorkingConditionResidence>
        </InfectionChanceSourceNameMapping>
        <ResolverConfigs>
          <Item>
            <FileName>data/graphics/effects/city_incidents/fire/stories/ci_fire_story_02.cfg</FileName>
            <Weight>100</Weight>
            <SpawnPlace>FEEDBACK_SPACE</SpawnPlace>
          </Item>
        </ResolverConfigs>
        <FreeSpaceSpawn>
          <ChunkSize>2</ChunkSize>
          <NeededSize>0.75</NeededSize>
          <SearchDistanceScale>1.5</SearchDistanceScale>
          <MinimumSpawnNumber>2</MinimumSpawnNumber>
          <MinUnitDistance>1.05</MinUnitDistance>
          <MaxSpawnPerChunk>0.25</MaxSpawnPerChunk>
        </FreeSpaceSpawn>
        <DangerUnsafeExtents>1</DangerUnsafeExtents>
        <DangerSafeExtents>3</DangerSafeExtents>
        <ResolverNextToCarSpawnRight>data/graphics/effects/city_incidents/fire/stories/ci_fire_story_01.cfg</ResolverNextToCarSpawnRight>
        <ResolverNextToCarSpawnLeft>data/graphics/effects/city_incidents/fire/stories/ci_fire_story_03.cfg</ResolverNextToCarSpawnLeft>
      </Incident>
      <Text>
        <LocaText>
          <English>
            <Text>Fire</Text>
            <Status>Exported</Status>
            <ExportCount>1</ExportCount>
          </English>
        </LocaText>
        <LineID>25920</LineID>
      </Text>
      <IncidentEffectConfiguration>
        <DummyEffectInformation>
          <DummyEffects>
            <Vertical>
              <ConfigFiles>
                <Item>
                  <Path>data/graphics/effects/city_incidents/fire/fire_vert_01.cfg</Path>
                  <Weight>100</Weight>
                  <UseDummyScale>1</UseDummyScale>
                </Item>
              </ConfigFiles>
            </Vertical>
            <Horizontal>
              <ConfigFiles>
                <Item>
                  <Path>data/graphics/effects/city_incidents/fire/fire_01.cfg</Path>
                  <Weight>100</Weight>
                  <UseDummyScale>1</UseDummyScale>
                </Item>
              </ConfigFiles>
            </Horizontal>
            <General>
              <ConfigFiles>
                <Item>
                  <Path>data/graphics/effects/city_incidents/fire/fire_smoke_01.cfg</Path>
                  <Weight>100</Weight>
                  <UseDummyScale>1</UseDummyScale>
                </Item>
              </ConfigFiles>
            </General>
          </DummyEffects>
          <FallbackConfig>
            <SpawnBlockSize>2</SpawnBlockSize>
            <RandomBoundsPercentage>75</RandomBoundsPercentage>
            <Scale>0.5</Scale>
          </FallbackConfig>
          <DummyFallbackUsage>DUMMY_OR_FALLBACK</DummyFallbackUsage>
        </DummyEffectInformation>
      </IncidentEffectConfiguration>
    </Values>
  </Asset>
</Assets>