<?xml version="1.0" encoding="utf-8"?>
<Assets Count="16">
  <Asset>
    <Template>UplayReward</Template>
    <Values>
      <Standard>
        <GUID>410005</GUID>
        <Name>ANNO7REWARD01</Name>
      </Standard>
      <UplayReward>
        <UplayRewardID>ANNO7REWARD01</UplayRewardID>
        <RewardName>15618</RewardName>
      </UplayReward>
      <Locked>
        <Scope>Account</Scope>
      </Locked>
    </Values>
  </Asset>
  <Asset>
    <Template>UplayReward</Template>
    <Values>
      <Standard>
        <GUID>410004</GUID>
        <Name>ANNO7REWARD02</Name>
      </Standard>
      <UplayReward>
        <UplayRewardID>ANNO7REWARD02</UplayRewardID>
        <UplayRewardUnlocks>
          <Item>
            <UplayRewardUnlock>100460</UplayRewardUnlock>
          </Item>
          <Item>
            <UplayRewardUnlock>500964</UplayRewardUnlock>
          </Item>
        </UplayRewardUnlocks>
        <UplayRewardPoints>50</UplayRewardPoints>
        <RewardName>15619</RewardName>
      </UplayReward>
      <Locked>
        <Scope>Account</Scope>
      </Locked>
    </Values>
  </Asset>
  <Asset>
    <Template>UplayReward</Template>
    <Values>
      <Standard>
        <GUID>410006</GUID>
        <Name>ANNO7REWARD03</Name>
      </Standard>
      <UplayReward>
        <UplayRewardID>ANNO7REWARD03</UplayRewardID>
        <UplayRewardUnlocks>
          <Item>
            <UplayRewardUnlock>100675</UplayRewardUnlock>
          </Item>
          <Item>
            <UplayRewardUnlock>500963</UplayRewardUnlock>
          </Item>
        </UplayRewardUnlocks>
        <UplayRewardPoints>30</UplayRewardPoints>
        <RewardName>15620</RewardName>
      </UplayReward>
      <Locked>
        <Scope>Account</Scope>
      </Locked>
    </Values>
  </Asset>
  <Asset>
    <Template>UplayReward</Template>
    <Values>
      <Standard>
        <GUID>410007</GUID>
        <Name>ANNO7REWARD04</Name>
      </Standard>
      <UplayReward>
        <UplayRewardID>ANNO7REWARD04</UplayRewardID>
        <UplayRewardUnlocks>
          <Item>
            <UplayRewardUnlock>100676</UplayRewardUnlock>
          </Item>
          <Item>
            <UplayRewardUnlock>500981</UplayRewardUnlock>
          </Item>
        </UplayRewardUnlocks>
        <UplayRewardPoints>30</UplayRewardPoints>
        <RewardName>15621</RewardName>
      </UplayReward>
      <Locked>
        <Scope>Account</Scope>
      </Locked>
    </Values>
  </Asset>
  <Asset>
    <Template>UplayReward</Template>
    <Values>
      <Standard>
        <GUID>410008</GUID>
        <Name>ANNO7REWARD05</Name>
      </Standard>
      <UplayReward>
        <UplayRewardID>ANNO7REWARD05</UplayRewardID>
        <UplayRewardUnlocks>
          <Item>
            <UplayRewardUnlock>500972</UplayRewardUnlock>
          </Item>
        </UplayRewardUnlocks>
        <UplayRewardPoints>10</UplayRewardPoints>
        <RewardName>15622</RewardName>
      </UplayReward>
      <Locked>
        <Scope>Account</Scope>
      </Locked>
    </Values>
  </Asset>
  <Asset>
    <Template>UplayReward</Template>
    <Values>
      <Standard>
        <GUID>410009</GUID>
        <Name>ANNO7REWARD06</Name>
      </Standard>
      <UplayReward>
        <UplayRewardID>ANNO7REWARD06</UplayRewardID>
        <UplayRewardUnlocks>
          <Item>
            <UplayRewardUnlock>500962</UplayRewardUnlock>
          </Item>
        </UplayRewardUnlocks>
        <UplayRewardPoints>10</UplayRewardPoints>
        <RewardName>15623</RewardName>
      </UplayReward>
      <Locked>
        <Scope>Account</Scope>
      </Locked>
    </Values>
  </Asset>
  <Asset>
    <Template>UplayReward</Template>
    <Values>
      <Standard>
        <GUID>410010</GUID>
        <Name>ANNO7REWARD07</Name>
      </Standard>
      <UplayReward>
        <UplayRewardID>ANNO7REWARD07</UplayRewardID>
        <UplayRewardUnlocks>
          <Item>
            <UplayRewardUnlock>500979</UplayRewardUnlock>
          </Item>
        </UplayRewardUnlocks>
        <UplayRewardPoints>10</UplayRewardPoints>
        <RewardName>15624</RewardName>
      </UplayReward>
      <Locked>
        <Scope>Account</Scope>
      </Locked>
    </Values>
  </Asset>
  <Asset>
    <Template>UplayReward</Template>
    <Values>
      <Standard>
        <GUID>410011</GUID>
        <Name>ANNO7REWARD08</Name>
      </Standard>
      <UplayReward>
        <UplayRewardID>ANNO7REWARD08</UplayRewardID>
        <UplayRewardUnlocks>
          <Item>
            <UplayRewardUnlock>102229</UplayRewardUnlock>
          </Item>
          <Item>
            <UplayRewardUnlock>103047</UplayRewardUnlock>
          </Item>
        </UplayRewardUnlocks>
        <UplayRewardPoints>20</UplayRewardPoints>
        <RewardName>16852</RewardName>
      </UplayReward>
      <Locked>
        <Scope>Account</Scope>
      </Locked>
    </Values>
  </Asset>
  <Asset>
    <Template>UplayReward</Template>
    <Values>
      <Standard>
        <GUID>410012</GUID>
        <Name>ANNO7REWARD09</Name>
      </Standard>
      <UplayReward>
        <UplayRewardID>ANNO7REWARD09</UplayRewardID>
        <UplayRewardUnlocks>
          <Item>
            <UplayRewardUnlock>102383</UplayRewardUnlock>
          </Item>
          <Item>
            <UplayRewardUnlock>103048</UplayRewardUnlock>
          </Item>
        </UplayRewardUnlocks>
        <UplayRewardPoints>20</UplayRewardPoints>
        <RewardName>16853</RewardName>
      </UplayReward>
      <Locked>
        <Scope>Account</Scope>
      </Locked>
    </Values>
  </Asset>
  <Asset>
    <Template>UplayReward</Template>
    <Values>
      <Standard>
        <GUID>410013</GUID>
        <Name>ANNO7REWARD10</Name>
      </Standard>
      <UplayReward>
        <UplayRewardID>ANNO7REWARD10</UplayRewardID>
        <UplayRewardUnlocks>
          <Item>
            <UplayRewardUnlock>501550</UplayRewardUnlock>
          </Item>
        </UplayRewardUnlocks>
      </UplayReward>
      <Locked>
        <Scope>Account</Scope>
      </Locked>
    </Values>
  </Asset>
  <Asset>
    <Template>UplayReward</Template>
    <Values>
      <Standard>
        <GUID>410014</GUID>
        <Name>ANNO7REWARD11</Name>
      </Standard>
      <UplayReward>
        <UplayRewardID>ANNO7REWARD11</UplayRewardID>
        <UplayRewardUnlocks>
          <Item>
            <UplayRewardUnlock>501518</UplayRewardUnlock>
          </Item>
        </UplayRewardUnlocks>
      </UplayReward>
      <Locked>
        <Scope>Account</Scope>
      </Locked>
    </Values>
  </Asset>
  <Asset>
    <Template>UplayReward</Template>
    <Values>
      <Standard>
        <GUID>410015</GUID>
        <Name>ANNO7REWARD12</Name>
      </Standard>
      <UplayReward>
        <UplayRewardID>ANNO7REWARD12</UplayRewardID>
        <UplayRewardUnlocks>
          <Item>
            <UplayRewardUnlock>501519</UplayRewardUnlock>
          </Item>
        </UplayRewardUnlocks>
      </UplayReward>
      <Locked>
        <Scope>Account</Scope>
      </Locked>
    </Values>
  </Asset>
  <Asset>
    <Template>UplayReward</Template>
    <Values>
      <Standard>
        <GUID>410016</GUID>
        <Name>ANNO7REWARD13</Name>
      </Standard>
      <UplayReward>
        <UplayRewardID>ANNO7REWARD13</UplayRewardID>
        <UplayRewardUnlocks>
          <Item>
            <UplayRewardUnlock>501551</UplayRewardUnlock>
          </Item>
        </UplayRewardUnlocks>
      </UplayReward>
      <Locked>
        <Scope>Account</Scope>
      </Locked>
    </Values>
  </Asset>
  <Asset>
    <Template>UplayReward</Template>
    <Values>
      <Standard>
        <GUID>410017</GUID>
        <Name>ANNO7REWARD14</Name>
      </Standard>
      <UplayReward>
        <UplayRewardID>ANNO7REWARD14</UplayRewardID>
        <UplayRewardUnlocks>
          <Item>
            <UplayRewardUnlock>501552</UplayRewardUnlock>
          </Item>
        </UplayRewardUnlocks>
      </UplayReward>
      <Locked>
        <Scope>Account</Scope>
      </Locked>
    </Values>
  </Asset>
  <Asset>
    <Template>UplayReward</Template>
    <Values>
      <Standard>
        <GUID>410018</GUID>
        <Name>ANNO7REWARD15</Name>
      </Standard>
      <UplayReward>
        <UplayRewardID>ANNO7REWARD15</UplayRewardID>
        <UplayRewardUnlocks>
          <Item>
            <UplayRewardUnlock>501563</UplayRewardUnlock>
          </Item>
        </UplayRewardUnlocks>
      </UplayReward>
      <Locked>
        <Scope>Account</Scope>
      </Locked>
    </Values>
  </Asset>
  <Asset>
    <Template>UplayReward</Template>
    <Values>
      <Standard>
        <GUID>410019</GUID>
        <Name>ANNO7REWARD16</Name>
      </Standard>
      <UplayReward>
        <UplayRewardID>ANNO7REWARD16</UplayRewardID>
        <UplayRewardUnlocks>
          <Item>
            <UplayRewardUnlock>102892</UplayRewardUnlock>
          </Item>
          <Item>
            <UplayRewardUnlock>103049</UplayRewardUnlock>
          </Item>
        </UplayRewardUnlocks>
      </UplayReward>
      <Locked>
        <Scope>Account</Scope>
      </Locked>
    </Values>
  </Asset>
</Assets>